py_rename/__init__.py
py_rename/__main__.py
py_rename/main.py
py_rename/py_rename.py
py_rename/version.py
src/__init__.py
src/__main__.py
src/main.py
src/py_rename.py
src/version.py
py_rename-1.4.0.dist-info/LICENSE
py_rename-1.4.0.dist-info/METADATA
py_rename-1.4.0.dist-info/WHEEL
py_rename-1.4.0.dist-info/entry_points.txt
py_rename-1.4.0.dist-info/top_level.txt
py_rename-1.4.0.dist-info/RECORD
